README.md
setup.py
weasyform/FormFinisher.py
weasyform/__init__.py
weasyform.egg-info/PKG-INFO
weasyform.egg-info/SOURCES.txt
weasyform.egg-info/dependency_links.txt
weasyform.egg-info/requires.txt
weasyform.egg-info/top_level.txt